codegra_fs/__init__.py
codegra_fs/api_consumer.py
codegra_fs/cgapi.py
codegra_fs/cgfs.py
codegra_fs/cgfs_types.py
codegra_fs/constants.py
codegra_fs/gui.py
codegra_fs/utils.py
CodeGra.fs-0.5.0.dist-info/LICENSE
CodeGra.fs-0.5.0.dist-info/METADATA
CodeGra.fs-0.5.0.dist-info/WHEEL
CodeGra.fs-0.5.0.dist-info/entry_points.txt
CodeGra.fs-0.5.0.dist-info/top_level.txt
CodeGra.fs-0.5.0.dist-info/RECORD
