Metadata-Version: 2.1
Name: CodeGra.fs
Version: 0.5.0
Summary: File-system for CodeGrade instances
Home-page: UNKNOWN
Author: The CodeGrade team
Author-email: info@codegra.de
License: UNKNOWN
Platform: UNKNOWN
Classifier: Programming Language :: Python :: 3
Classifier: License :: OSI Approved :: GNU Affero General Public License v3 or later (AGPLv3+)
Classifier: Operating System :: POSIX
Classifier: Operating System :: MacOS
Requires-Dist: PyQt5 (<6.0.0,>=5.11.3)
Requires-Dist: appdirs (<2.0.0,>=1.4.3)
Requires-Dist: fusepy (<4.0.0,>3.0.0)
Requires-Dist: requests (>=2.20.0)
